markdown_ratings/__init__.py
markdown_ratings/main.py
markdown_ratings-0.1.2.dist-info/LICENSE.md
markdown_ratings-0.1.2.dist-info/WHEEL
markdown_ratings-0.1.2.dist-info/METADATA
markdown_ratings-0.1.2.dist-info/RECORD
