Metadata-Version: 2.1
Name: markdown-ratings
Version: 0.1.2
Summary: A Markdown plugin to show star ratings on your page.
License: MIT
Author: Johan Vergeer
Author-email: johanvergeer@gmail.com
Requires-Python: >=3.7,<4.0
Classifier: License :: OSI Approved :: MIT License
Classifier: Programming Language :: Python :: 3
Classifier: Programming Language :: Python :: 3.7
Classifier: Programming Language :: Python :: 3.8
Requires-Dist: markdown (>=3.1.1,<4.0.0)
